gslides/__init__.py
gslides/chart.py
gslides/colors.py
gslides/config.py
gslides/frame.py
gslides/presentation.py
gslides/spreadsheet.py
gslides/table.py
gslides/utils.py
gslides/config/base_palettes.yaml
gslides/config/chart_params.yaml
gslides/config/color_mapping.yaml
gslides/config/presentation_params.yaml
tests/__init__.py
tests/test_chart.py
tests/test_colors.py
tests/test_frame.py
tests/test_presentation.py
tests/test_spreadsheet.py
tests/test_table.py
tests/test_utils.py
gslides-0.1.1.dist-info/AUTHORS.rst
gslides-0.1.1.dist-info/LICENSE
gslides-0.1.1.dist-info/METADATA
gslides-0.1.1.dist-info/WHEEL
gslides-0.1.1.dist-info/top_level.txt
gslides-0.1.1.dist-info/RECORD
