Metadata-Version: 2.1
Name: gslides
Version: 0.1.1
Summary: Wrapper around Google APIs to create charts in Google Slides with python
Home-page: https://github.com/michael-gracie/gslides
Author: Michael Gracie
Author-email: 12mpggslides@gmail.com
License: MIT License
Project-URL: Documentation, https://github.com/pages/michael-gracie/gslides/build/html/index.html
Project-URL: Bug Tracker, https://michael-gracie.github.io/gslides//issues
Project-URL: Source Code, https://michael-gracie.github.io/gslides/
Platform: UNKNOWN
Classifier: Intended Audience :: Developers
Classifier: Natural Language :: English
Classifier: Operating System :: OS Independent
Classifier: Programming Language :: Python
Classifier: Programming Language :: Python :: 3.7
Requires-Python: >=3.7.0
License-File: LICENSE
License-File: AUTHORS.rst
Requires-Dist: google-api-core (>=1.26.2)
Requires-Dist: google-api-python-client (>=2.0.2)
Requires-Dist: google-auth (>=1.28.0)
Requires-Dist: google-auth-httplib2 (>=0.1.0)
Requires-Dist: google-auth-oauthlib (>=0.4.3)
Requires-Dist: googleapis-common-protos (>=1.53.0)
Requires-Dist: tabulate (>=0.8.9)
Requires-Dist: pandas (>=1.1.5)
Requires-Dist: numpy (>=1.19.5)
Requires-Dist: PyYAML (>=5.4.1)
Requires-Dist: requests (>=2.22.0)
Requires-Dist: ipython (>=7.16.1)
Provides-Extra: dev
Requires-Dist: coverage ; extra == 'dev'
Requires-Dist: pytest ; extra == 'dev'
Requires-Dist: pytest-cov ; extra == 'dev'
Requires-Dist: pytest-pylint ; extra == 'dev'
Requires-Dist: mypy ; extra == 'dev'
Requires-Dist: sphinx ; extra == 'dev'
Requires-Dist: sphinx-rtd-theme ; extra == 'dev'
Requires-Dist: furo ; extra == 'dev'
Requires-Dist: pylint ; extra == 'dev'
Requires-Dist: pre-commit ; extra == 'dev'
Requires-Dist: black ; extra == 'dev'
Requires-Dist: isort ; extra == 'dev'
Requires-Dist: check-manifest ; extra == 'dev'
Requires-Dist: flake8 ; extra == 'dev'
Provides-Extra: docs
Requires-Dist: sphinx ; extra == 'docs'
Requires-Dist: sphinx-rtd-theme ; extra == 'docs'
Requires-Dist: furo ; extra == 'docs'
Provides-Extra: qa
Requires-Dist: pylint ; extra == 'qa'
Requires-Dist: pre-commit ; extra == 'qa'
Requires-Dist: black ; extra == 'qa'
Requires-Dist: isort ; extra == 'qa'
Requires-Dist: mypy ; extra == 'qa'
Requires-Dist: check-manifest ; extra == 'qa'
Requires-Dist: flake8 ; extra == 'qa'
Provides-Extra: test
Requires-Dist: coverage ; extra == 'test'
Requires-Dist: pytest ; extra == 'test'
Requires-Dist: pytest-cov ; extra == 'test'
Requires-Dist: pytest-pylint ; extra == 'test'
Requires-Dist: mypy ; extra == 'test'
